README.md
setup.py
pyopenvpn/__init__.py
pyopenvpn/openvpn.py
pyopenvpn.egg-info/PKG-INFO
pyopenvpn.egg-info/SOURCES.txt
pyopenvpn.egg-info/dependency_links.txt
pyopenvpn.egg-info/top_level.txt