Metadata-Version: 2.1
Name: pyopenvpn
Version: 0.0.3
Summary: manage openvpn
Home-page: https://github.com/x-hezhang/pyopenvpn
Author: zhanghe
Author-email: x_hezhang@126.com
License: GPLv3
Keywords: openvpn
Platform: UNKNOWN
